README.txt
setup.py
TxMap.egg-info/PKG-INFO
TxMap.egg-info/SOURCES.txt
TxMap.egg-info/dependency_links.txt
TxMap.egg-info/top_level.txt
TxMap.egg-info/zip-safe
txmap/__init__.py
txmap/config.py
txmap/map.py