Metadata-Version: 1.1
Name: TxMap
Version: 0.0.5
Summary: A hepler tools for tencent map api
Home-page: https://github.com/block-cat/txmap
Author: blackcat
Author-email: kfx2007@163.com
License: GNU
Keywords: Tencent Map Tools
Platform: UNKNOWN
Classifier: License :: OSI Approved :: GNU Affero General Public License v3
Classifier: Programming Language :: Python
Classifier: Operating System :: OS Independent
Classifier: Topic :: Scientific/Engineering :: Astronomy
Classifier: Topic :: Scientific/Engineering :: GIS
Classifier: Topic :: Scientific/Engineering :: Mathematics
Classifier: Intended Audience :: Science/Research
Classifier: Intended Audience :: Developers
Classifier: Intended Audience :: Information Technology
